<document xml:lang="eng" id="no_id"><header><title>Anaras - Environment - Place Names</title><genre code="facta"/><author><person firstname="Ilmari" lastname="Mattus" sex="m" born="" nationality="FI"/></author><year>2006</year><wordcount>1438</wordcount><conversion_status type="standard"/><availability><license type="standard"/></availability><multilingual/><origFileName>http://www.samimuseum.fi/anaras/english/ymparisto/top.html</origFileName><parallel_text xml:lang="fin" location="top.html"/><parallel_text xml:lang="smn" location="top.html"/><metadata><uncomplete/></metadata><version>XSLtemplate $Revision: 150288 $; file-specific xsl  Revision; common.xsl  $Revision$; </version></header><body><p>Place Names</p>
<p>Ancestral Territories</p>
<p>Building Tradition</p>
<p>Place names here in the Inari region tell, among other things, how the lion’s share of place names is derived from living nature. The predominant share of place names in the Inari region come from fish and this tells us that we were above all a fishing people, but also a hunting people; at least used to be. Fish appear <em type="italic">338 </em>times of which perch are at the head ( <em type="italic">82 times </em>). Second place is taken <em type="italic">318 </em>times by animals, of which reindeer and various derivatives appear ( <em type="italic">59 </em>times). A hardy third place is occupied by people with names appearing in <em type="italic">278 </em>place names with Antti in the lead ( <em type="italic">36 </em>). Fourth place is taken by birds which are met in <em type="italic">242 </em>place names, with the most being red throated divers ( <em type="italic">43 </em>times) but not one great northern diver. We can conclude from this that in olden days these two bird species were considered the same and I still believed, for example, in the 1980s that the great northern diver’s Inari Sámi name was <em type="italic">kähtee </em>; I had not even heard of the name <em type="italic">tuhtuu. </em></p>
<p>Trees and plants occupy fourth place at <em type="italic">227 </em>times with pine in the lead ( <em type="italic">42 </em>times). The sixth place is taken by gods, shamans and nature spirits which show up <em type="italic">82 </em>times, Ákku and Äijih (a female god and a male god) in the lead ( <em type="italic">43 </em>times). Seventh place belongs to insects which are met in names <em type="italic">20 </em>times, blackflys most (4 times). The absolute last place is taken by berries and mushrooms, even though they were important to people. They show up only <em type="italic">16 </em>times of which blueberries ( <em type="italic">7 </em>times) are at the top. All in all, the above mentioned species appear in <em type="italic">1502 </em>place names, over one fifth of all Inari Sámi place names. My research has not yet extended to North Sámi and Finnish language place names in this respect. The names in question are nevertheless mostly the same names as the Inari Sámi names, i.e. they are Finnish and North Sámi translations. </p>
<p>What kind of names then are the four fifths left over? They are based on appellations, i.e. they are based on names relating to the land and appear most often in the main portions, but also in the adjuncts. There are a few place names with these kinds of words in both the main and adjunct parts, such as in <em type="italic">Suáluičuálmáásuálui </em>– Island, <em type="italic"><span type="quote" xml:lang="nob">“Island Channel Island”</span> </em>, and <em type="italic">Suáluinyeresuálui – Island, <span type="quote" xml:lang="nob">“Island Long Channel Island”</span> </em>, which has been translated into Finnish as <span type="quote" xml:lang="fkv">“nuotoon”</span>, in <em type="italic">Nuoransaari </em>. All in all, there are over 6000 Inari Sámi place names, Finnish names somewhat less, North Sámi names over 2000, Skolt language names about two hundred and the same amount for seine-fishing grounds. Of all the fishing grounds, the exact locations of the seine-fishing grounds are not all known; neither will we be able to determine them. Altogether the registered and mapped names of locations are about 14,000. </p>
<p>Back to Top</p>
<p><em type="italic">Altogether the Inari Sámi geographic appellatives are about 300. The following is a Top-40 list or 40 most frequent appellative place names in order of preference: </em></p>
<p><em type="italic">1. jävri + jáávráš + jávrádâh = </em>lake (and various forms) <em type="italic">1956 </em>times <em type="italic">2. vääri + váárááš + värehâš = </em>ridge (and various forms) <em type="italic">712 </em>times <em type="italic">3. suálui + suolluš + lássá = </em>island (and various forms) <em type="italic">629 </em>times <em type="italic">4. juuhâ + vei + juuvâš + aajâ = </em>river (and various forms) + source <em type="italic">552 </em>times <em type="italic">5 </em>. <em type="italic">njargâ + njaargâš + njargâstâh = </em>peninsula (and various forms) <em type="italic">537 </em>times <em type="italic">6. luohtâ + luovtâš = </em>bay (and various forms) <em type="italic">480 </em>times <em type="italic">7. luobâl + luobbâlâš = </em>pond-like widening within a stream <em type="italic">233 </em>times <em type="italic">8. jeggi + jiägáš = </em>bog and diminutive form <em type="italic">198 </em>times <em type="italic">9. uáivi + uáiváš = </em>top and diminutive form <em type="italic">185 </em>times <em type="italic">10. keđgi + kiäđgáš = </em>rock and diminutive form <em type="italic">157 </em>times <em type="italic">11. čuálmi + čuálmáš = </em>channel and diminutive form <em type="italic">152 </em>times <em type="italic">12. ruávi + puállám = </em>rocky bulge, burnt hill + burnt hill <em type="italic">149 </em>times <em type="italic">13. vyeppee = </em>bay in a river <em type="italic">132 </em>times <em type="italic">14. láddu + lááduš = </em>pond and diminutive form <em type="italic">117 </em>times <em type="italic">15. čielgi + siälgáš = </em>massif and diminutive form <em type="italic">114 </em>times <em type="italic">16. kuoškâ = </em>rapids <em type="italic">97 </em>times <em type="italic">17. vuonâ + vuonâš </em>= fjord <em type="italic">89 </em>times <em type="italic">18. kieddi + kiäddáš </em>= field <em type="italic">72 </em>times <em type="italic">19. </em><em type="italic">moorâst = </em>low birch-clad ridge <em type="italic">70 </em>times <em type="italic">20. eennâm = </em>land <em type="italic">63 </em>times <em type="italic">21. pähti + páávtáš = </em>steep rocky wall <em type="italic">61 </em>times <em type="italic">22. puolžâ = </em>ridge/esker <em type="italic">54 </em>times <em type="italic">23. skäiđi + skááiđáš = </em>woods (woods between rivers) <em type="italic">52 </em>times <em type="italic">24. uáivuš, </em>river mouth in a lake <em type="italic">48 </em>times <em type="italic">25. savo ~ savvoon + savonâš = </em>calm pool <em type="italic">44 </em>times <em type="italic">26. čukkâ ~ čokke ~ čohhááš + čummâ = </em>hill + peak <em type="italic">43 </em>times <em type="italic">27. pohe + povvááš = </em>small, cramped place + valley <em type="italic">42 </em>times <em type="italic">28. myetki + muáđháš + muáđhád = </em>stage of a journey <em type="italic">41 </em>times <em type="italic">29. vuodâs = </em>sandy beach <em type="italic">38 </em>times <em type="italic">30. tupesaje </em>= cottage location <em type="italic">35 </em>times <em type="italic">31. käldee </em>= spring, opening <em type="italic">33 </em>times <em type="italic">32. juovâ = </em>cave ~ rock field ~ boulder field <em type="italic">31 </em>times <em type="italic">33. ämmir + tiävá = </em>knoll ~ hillock <em type="italic">29 </em>times <em type="italic">34. kuolbâ + kuolbânâš = </em>sandy heath with juniper <em type="italic">28 </em>times <em type="italic">35. ävži = </em>ravine <em type="italic">27 </em>times <em type="italic">36. kárgu = </em>shoal/rock <em type="italic">25 </em>times <em type="italic">37. nyeri + nuárááš = </em>long and thin channel <em type="italic">22 </em>times <em type="italic">38. viälmá </em>= deep spot in a slow river <em type="italic">21 </em>times <em type="italic">39. kaavâ = </em>gentle bend <em type="italic">20 </em>times <em type="italic">40. puornâ </em>= storage pit <em type="italic">18 </em>times </p>
<p>And as we noticed, there are no words related to fells on the list, though there is a significant amount of fells in the Inari region. It only occupies 41st place, appearing 17 times, of which the greatest part are located outside of the Inari region. Forty favored terrain-related appellatives appear as many as 7254 times. The number of appearances of the rest of the 260 terrain-related appellatives has not been counted. <em type="italic">The kinds of human constructions or technical implements that are found in the place names of the Inari region: </em>1. <em type="italic">The predominant word encountered, </em><em type="italic">kuáti </em>= kota, Lapp hut <em type="italic">146 </em>times 2. A good second, <em type="italic">tupe </em>= cottage, <em type="italic">107 </em>times 3. Third most encountered, <em type="italic">lyevi </em>= stack, <em type="italic">19 </em>times 4. Fourth is seine net – related words, <em type="italic">koldem </em>ja <em type="italic">nyetti </em>= seine fishing and seine <em type="italic">18 </em>times, but surprisingly the same amount is attained by <em type="italic">puornâ </em>= storage pit for meat and fish 5. Fifth place attained by <em type="italic">äiđi </em>= corral, fence <em type="italic">16 </em>times 6. Sixth place, <em type="italic">láávu </em>= conical tent <em type="italic">14 </em>times 7. Seventh place is <em type="italic">ákšu </em>= knife, <em type="italic">11 </em>times 8. Eighth place is taken by <em type="italic">kerris </em>= sledge and <em type="italic">puárree </em>= raft, <em type="italic">10 </em>times 9. Ninth place, <em type="italic">käärbis </em>= boat and <em type="italic">piärtušm </em>= deer hunting barrier fence, <em type="italic">9 </em>times by both 10 Tenth place is taken by <em type="italic">viermi </em>= net, <em type="italic">8 </em>times 11. In eleventh place are <em type="italic">lyevdi </em>= board and <em type="italic">káskástoh </em>= fall trap, <em type="italic">7 </em>times 12. In twelfth place <em type="italic">huonâs </em>= wolf trap, <em type="italic">6 </em>times 13. In thirteenth place are the implements <em type="italic">nijbe </em>= Lapp knife, <em type="italic">láávtáš </em>= high platform for storing meat, <em type="italic">árdu </em>= drying rack (for meat and fish), <em type="italic">tävgi </em>and <em type="italic">pelbi </em>= bow and sharp arrow, as well as <em type="italic">pisso </em>= gun, <em type="italic">5 </em>times each 14. In fourteenth place are <em type="italic">suárváš </em>= pole for fishing nets used in pulling, <em type="italic">saaveeh </em>= ski and <em type="italic">puvre </em>= storage hut, often of peat, <em type="italic">4 </em>times each 15. Fifteenth place is shared by <em type="italic">säitti </em>= spear, <em type="italic">čyeimi </em>= pole and <em type="italic">hirsâ </em>log, <em type="italic">3 </em>times each 16. Seven words share sixteenth place: <em type="italic">veeččir </em>= hammer, <em type="italic">liššá </em>= scythe <em type="italic">kaŋgâ </em>= handspike, <em type="italic">läbži </em>= strap, <em type="italic">stávrá </em>= pole, <em type="italic">naavit </em>= cowshed and <em type="italic">láátu </em>= barn, <em type="italic">2 </em>times each 17. The last place is shared by eight: <em type="italic">sivlá </em>= long fence used in separations, <em type="italic">háárááv </em>= rake, <em type="italic">puuvko </em>= knife, <em type="italic">suábbi </em>= pole, <em type="italic">kiällár </em>= cellar, <em type="italic">kiämppá </em>= cabin, <em type="italic">syermi </em>= dry pine with many branches for drying food ja <em type="italic">tävgi </em>= bow, once each. In all, these constructions, tools and devices appear in adjuncts <em type="italic">492 </em>times. </p>
<p xml:lang="smn">Ilmari Mattus</p>
<p>Ritakoski Rapids of Juutuajoki River  with Otsamo fell in the background.</p>
<p>The red-throated diver is a common water  bird of Lake Inari and a favorite bird’s name  among place names.</p>
<p xml:lang="smn">Ukko in Lake Ukonjärvi.</p>
<p><em type="italic">Nature and People in Place Names in the Inari Region </em></p>
<p><em type="italic">What Do Place Names Tell Us? </em></p>
<p>Back to Top</p>
<p xml:lang="smn">© 2006 Sámi musea Siida &amp; Anarâškielâ servi</p>
<p xml:lang="sme">siida@samimuseum.fi</p>
</body></document>
