<document xml:lang="eng" id="no_id"><header><title/><genre code="ficti"/><author><unknown/></author><wordcount>117</wordcount><conversion_status type="standard"/><availability><free/></availability><submitter name="Sindre Reino Trosterud" email="sindre.reino.trosterud@gmail.com"/><multilingual><language xml:lang="eng"/></multilingual><metadata><uncomplete/></metadata><version>XSLtemplate $Revision$; file-specific xsl  Revision; common.xsl  $Revision$; </version></header>
<body>
<p>(From Broken Flowers Soundtrack)</p>
<p>Words disappear, Words weren't so clear, Only echos passing through the night.</p>
<p>The lines on my face, Your fingers once traced, Fading reflection of what was.- mellomspill</p>
<p>Thoughts re-arrange, Familar now strange, All my skin is drifting on the wind.</p>
<p>Spring brings the rain, With winter comes pain, Every season has an end.stikk: I try to see through the disguise, But the clouds were there, Blocking out the sun (the sun).- mellomspill</p>
<p>Thoughts re-arrange, Familar now strange, All my skin is drifting on the wind.</p>
<p>Spring brings the rain, With winter comes pain, Every season has an end.</p>
<p>There's an end, There's an end, There's an end, There's an end, There's an end.</p>
</body></document>
